area_code_nanp/__init__.py
area_code_nanp/data/nanp.json
py_area_code_nanp-1.0.1.dist-info/LICENSE
py_area_code_nanp-1.0.1.dist-info/METADATA
py_area_code_nanp-1.0.1.dist-info/WHEEL
py_area_code_nanp-1.0.1.dist-info/top_level.txt
py_area_code_nanp-1.0.1.dist-info/RECORD
