Metadata-Version: 2.1
Name: py-area-code-nanp
Version: 1.0.1
Summary: Information about phone area codes in the North American Numbering Plan
Home-page: https://github.com/rylz/py-area-code-nanp
Author: Riley Patterson
Author-email: rileypatterson@gmail.com
License: UNKNOWN
Platform: UNKNOWN
Classifier: Programming Language :: Python :: 2
Classifier: Programming Language :: Python :: 3
Classifier: License :: OSI Approved :: MIT License
Classifier: Operating System :: OS Independent
Requires-Python: >=2.7
